[
  { "id": "skill-1", "name": "Eri silk weaving", "category": "Production" },
  { "id": "skill-2", "name": "Muga silk weaving", "category": "Production" },
  { "id": "skill-3", "name": "Hand spinning", "category": "Production" },
  { "id": "skill-4", "name": "Natural dyeing", "category": "Production" },
  { "id": "skill-5", "name": "Hand embroidery", "category": "Production" },
  { "id": "skill-6", "name": "Power loom operation", "category": "Production" },
  { "id": "skill-7", "name": "Design & pattern making", "category": "Creative" },
  { "id": "skill-8", "name": "Quality finishing", "category": "Production" },
  { "id": "skill-9", "name": "Silk reeling", "category": "Production" },
  { "id": "skill-10", "name": "Product marketing", "category": "Business" },
  { "id": "skill-11", "name": "Mulberry silk weaving", "category": "Production" },
  { "id": "skill-12", "name": "Tassar silk weaving", "category": "Production" },
  { "id": "skill-13", "name": "Muga sericulture", "category": "Production" },
  { "id": "skill-14", "name": "Eri cocoon rearing", "category": "Production" },
  { "id": "skill-15", "name": "Mulberry yarn spinning", "category": "Production" },
  { "id": "skill-16", "name": "Tassar reeling", "category": "Production" }
]
